datachat/__init__.py
datachat/cli.py
datachat-0.0.3.dist-info/LICENSE
datachat-0.0.3.dist-info/METADATA
datachat-0.0.3.dist-info/WHEEL
datachat-0.0.3.dist-info/RECORD
