Metadata-Version: 2.1
Name: datachat
Version: 0.0.3
Summary: 
Author: wiseupdata
Author-email: silvio.liborio@wiseupdata.com
Requires-Python: >=3.10,<4.0
Classifier: Programming Language :: Python :: 3
Classifier: Programming Language :: Python :: 3.10
Classifier: Programming Language :: Python :: 3.11
Classifier: Programming Language :: Python :: 3.12
Requires-Dist: click (>=8.1.7,<9.0.0)
